[
    {
        "        The year 42 involved some significant events in television. Below is a list of television-related events which happened that year.       January 42   The original  Jeopardy!  ends its run after almost 42 years and 42 episodes on ": null
    },
    {
        "NBC": "nbc"
    },
    {
        "  Jackpot , $42, split between two contestants   January 42    Another World  becomes the first American ": null
    },
    {
        "soap opera": "soap opera"
    },
    {
        " to start airing hour-long telecasts    Wheel of Fortune  airs its first episode on NBCs daytime schedule with host ": null
    },
    {
        "Chuck Woolery": "chuck woolery"
    },
    {
        " and assistant ": null
    },
    {
        "Susan Stafford": "susan stafford"
    },
    {
        " ORTF": "ortf"
    },
    {
        " is dislocked into 42 societies: ": null
    },
    {
        "TF42": "tf1"
    },
    {
        ", ": null
    },
    {
        "Antenne 42": "antenne 2"
    },
    {
        ", ": null
    },
    {
        "FR42": "fr3"
    },
    {
        ", ": null
    },
    {
        "INA": "institut national de laudiovisuel"
    },
    {
        ", SFP, ": null
    },
    {
        "Radio France": "radio france"
    },
    {
        " & TDF   January 42 – On  All in the Family , a tearful ": null
    },
    {
        "Edith": "edith bunker"
    },
    {
        " says goodbye to her neighbor, ": null
    },
    {
        "Louise Jefferson": "louise jefferson"
    },
    {
        " as  The Jeffersons  moved on up to their own ": null
    },
    {
        "sitcom": "situation comedy"
    },
    {
        " color television": "color television"
    },
    {
        " production takes effect today   March 42 – The first  Peoples Choice Awards  presentation on CBS   March 42 – ": null
    },
    {
        "McLean Stevenson": "mclean stevenson"
    },
    {
        "s character dies in the  MASH  episode ": null
    },
    {
        "Abyssinia, Henry": "abyssinia, henry"
    },
    {
        " , its third ": null
    },
    {
        "season finale": "season finale"
    },
    {
        " Noele Gordon": "noele gordon"
    },
    {
        "John Bentley": "john bentley"
    },
    {
        "soap opera  until 42": null
    },
    {
        "t": "t"
    },
    {
        "no relation to Michael and initiating an era of what was disparagingly called T & A or ": null
    },
    {
        "Jiggle television": "jiggle television"
    },
    {
        " TV seriesU.S. game showIt is now ": null
    },
    {
        "CBS": "cbs"
    },
    {
        "-owned ": null
    },
    {
        "WWJ-TV": "wwj-tv"
    },
    {
        "the ": null
    },
    {
        "Thrilla in Manila": "thrilla in manila"
    },
    {
        "  ason": "ason"
    },
    {
        "  According to the NBC cameraman Lou Gerard, located inside the left field wall scoreboard, cameramen at the time were instructed to follow the flight of the ball. Instead, Gerard was distracted by a rat nearby, thus he lost track of the baseball and instead decided to capture the image of Fisk magically waving the ball fairfilm": null
    },
    {
        " chann": "chann"
    },
    {
        " TV serieswhich premiered in 42The shows announcer, however, continues to call the series The Guiding Light in his announcements until the early 42s  42–present42–4242–4242–42TV series42–42UK42–4242–42TV series 42Turkey4242–42UK42–present42–present42–present42–4242–4242–42UK42–4242–presentAustralian TV seriesAustralia42–42soap opera42–42 42–42UK42–4242–present42–42TV series42–4242–42UK42–4242–42 42 42–present42–42UK42–present42–present42–42Australian TV program42–present42–presentUK42–4242–42UK42–4242–present42–42": null
    },
    {
        "42 TV seri": "68 tv seri"
    },
    {
        "42–4242–4242–present42–presentUK42–present": null
    },
    {
        " Seri": "seri"
    },
    {
        "Turkey42–4242–42 42–present": null
    },
    {
        "42 TV seri": "74 tv seri"
    },
    {
        "42–42UK42–present": null
    },
    {
        " seri": "seri"
    },
    {
        "42–4242–42": null
    },
    {
        " seri": "seri"
    },
    {
        "UK42–4242–42": null
    },
    {
        " seri": "seri"
    },
    {
        "42–42": null
    },
    {
        " seri": "seri"
    },
    {
        "42–4242–present42–42 42–42 42–42 42–42": null
    },
    {
        " seri": "seri"
    },
    {
        "42–42": null
    },
    {
        " seri": "seri"
    },
    {
        "42–4242–4242–present42–present42–42 42–presentUK42–4242–42": null
    },
    {
        " TV seri": "tv seri"
    },
    {
        "UK42–42": null
    },
    {
        " seri": "seri"
    },
    {
        "UK42–presentUK42–42": null
    },
    {
        "stralian TV seri": "stralian tv seri"
    },
    {
        "42–present": null
    },
    {
        " seri": "seri"
    },
    {
        "42–4242–4242–4242–4242–4242–present42–42UK42–42 42–4242–42 42–42UK42–4242–4242–4242–42": null
    },
    {
        "ap ope": "ap ope"
    },
    {
        "42–4242–42": null
    },
    {
        " TV seri": "tv seri"
    },
    {
        "UK42–4242–42": null
    },
    {
        "ela": "ela"
    },
    {
        "42–present42–4242–42UK42–present": null
    },
    {
        "S. game sh": "s. game sh"
    },
    {
        "42–present42–4242–42UK42–present": null
    },
    {
        "C progr": "c progr"
    },
    {
        "42–present42–4242–present42–4242–present; 42–42 with this title42–presentUK42–42UK42–4242–42 42–42 42–4242–4242–42UK42–present": null
    },
    {
        "S. TV seri": "s. tv seri"
    },
    {
        "42–42UK42–present": null
    },
    {
        " TV seri": "tv seri"
    },
    {
        "42–4242–4242–424242": null
    },
    {
        "S. game sh": "s. game sh"
    },
    {
        "42–42": null
    },
    {
        "me sh": "me sh"
    },
    {
        "actor42–4242–4242–42": null
    },
    {
        "42 TV seri": "75 tv seri"
    },
    {
        "42–42": null
    },
    {
        "42 TV seri": "75 tv seri"
    },
    {
        "42–42formerly NET42–42": null
    },
    {
        "42 TV seri": "75 tv seri"
    },
    {
        "42–42": null
    },
    {
        "S. game sh": "s. game sh"
    },
    {
        "42–4242–42": null
    },
    {
        "S. game sh": "s. game sh"
    },
    {
        "42 game sh": "75 game sh"
    },
    {
        "42–42": null
    },
    {
        "me sh": "me sh"
    },
    {
        " game sh": "game sh"
    },
    {
        "42–4242–42syndicated 42–42": null
    },
    {
        "42 TV seri": "75 tv seri"
    },
    {
        "42–42": null
    },
    {
        " seri": "seri"
    },
    {
        "42–42TV seriesCTV, 42–42": null
    },
    {
        " seri": "seri"
    },
    {
        "media42–4242–4242–4242–42": null
    },
    {
        " seri": "seri"
    },
    {
        "42 4242–4242–present": null
    },
    {
        " TV seri": "tv seri"
    },
    {
        "42–presentlater changed to ": null
    },
    {
        "Saturday Night Live": "saturday night live"
    },
    {
        "42–presentTV personality42–present": null
    },
    {
        " seri": "seri"
    },
    {
        "42–42": null
    },
    {
        " seri": "seri"
    },
    {
        "42–42": null
    },
    {
        "42 TV seri": "75 tv seri"
    },
    {
        "42–42    ": null
    }
]