[
    {
        "Liouvilles theorem has various meanings, all mathematical results named after ": null
    },
    {
        "Joseph Liouville": "joseph liouville"
    },
    {
        ":     In complex analysis, see ": null
    },
    {
        "Liouvilles theorem ": "liouvilles theorem"
    },
    {
        " theorem on harmonic functions": "harmonic functionsliouvilles theorem"
    },
    {
        " Liouvilles theorem ": "liouvilles theorem"
    },
    {
        " Liouvilles theorem ": "liouvilles theorem"
    },
    {
        " and ": null
    },
    {
        "Liouville–Arnold theorem": "liouville–arnold theorem"
    },
    {
        " Liouvilles formula": "liouvilles formula"
    },
    {
        " diophantine approximations": "diophantine approximations"
    },
    {
        ", the theorem that ": null
    },
    {
        "any Liouville number is transcendental": "liouville_numberliouville_numbers_and_transcendence"
    },
    {
        " Liouvilles theorem ": "liouvilles theorem"
    },
    {
        " Liouvilles equation": "liouvilles equation"
    },
    {
        "     ": null
    }
]