[
    {
        "This is a list of lists of universities and colleges.       ": null
    },
    {
        "Aerospace engineering": "List Of Aerospace Engineering Schools"
    },
    {
        " Agriculture": "List Of Agricultural Universities And Colleges"
    },
    {
        " Art schools": "List Of Art Schools"
    },
    {
        " Business": "Business Schoollists Of Business Schools"
    },
    {
        " Chiropractic": "List Of Chiropractic Schools"
    },
    {
        " Engineering": "List Of Engineering Schools"
    },
    {
        " Forestry": "List Of Forestry Universities And Colleges"
    },
    {
        " Law": "Lists Of Law Schools"
    },
    {
        " Maritime studies": "List Of Maritime Colleges"
    },
    {
        " Medicine": "List Of Medical Schools"
    },
    {
        " Music": "List Of University And College Schools Of Music"
    },
    {
        " Nanotechnology": "Nanotechnology Education"
    },
    {
        " Osteopathy": "List Of Osteopathic Colleges"
    },
    {
        " Pharmaceuticals": "List Of Pharmacy Schools"
    },
    {
        " Social Work": "List Of Universities With Programs In Social Work"
    },
    {
        "        Community colleges": "List Of Community Colleges"
    },
    {
        " For-profit universities and colleges": "List Of For-Profit Universities And Colleges"
    },
    {
        " Land-grant universities": "List Of Land-Grant Universities"
    },
    {
        " Liberal arts universities": "List Of Liberal Arts Colleges"
    },
    {
        " National universities": "National University"
    },
    {
        " Postgraduate-only institutions": "List Of Postgraduate-Only Institutions"
    },
    {
        " Private universities": "Private University"
    },
    {
        " Public universities": "Public University"
    },
    {
        " Research universities": "List Of Research Universities In The United States"
    },
    {
        " Technical universities": "List Of Institutions Using The Term   Institute Of Technology   Or   Polytechnic"
    },
    {
        " Sea-grant universities": "National Sea Grant College Program"
    },
    {
        " Space-grant universities": "National Space Grant College And Fellowship Program"
    },
    {
        " State universities and colleges": "List Of State Universities In The United States"
    },
    {
        " Unaccredited universities": "List Of Unaccredited Institutions Of Higher Learning"
    },
    {
        " Lists of universities and colleges by country": "Lists Of Universities And Colleges By Country"
    },
    {
        " List of largest universities": "List Of Largest Universities"
    },
    {
        "        Assemblies of God": "List Of Assemblies Of God Schools"
    },
    {
        " Catholic universities": "Catholic University"
    },
    {
        "   : ": null
    },
    {
        "Ecclesiastical universities": "Ecclesiastical University"
    },
    {
        "   : ": null
    },
    {
        "Benedictine colleges and universities": "List Of Benedictine Colleges And Universities"
    },
    {
        "   : ": null
    },
    {
        "Jesuit institutions": "List Of Jesuit Educational Institutions"
    },
    {
        "   : ": null
    },
    {
        "Opus Dei universities": "Opus Dei In Societyuniversities"
    },
    {
        "   : ": null
    },
    {
        "Pontifical universities": "Pontifical University"
    },
    {
        "   : ": null
    },
    {
        "International Council of Universities of Saint Thomas Aquinas": "International Council Of Universities Of Saint Thomas Aquinas"
    },
    {
        "   : ": null
    },
    {
        "International Federation of Catholic Universities": "International Federation Of Catholic Universities"
    },
    {
        " Churches of Christ": "List Of Universities And Colleges Affiliated With The Churches Of Christ"
    },
    {
        " Church of the Nazarene": "List Of Church Of The Nazarene Schools"
    },
    {
        " Christian churches and churches of Christ": "List Of Universities And Colleges Affiliated With The Christian Churches And Churches Of Christ"
    },
    {
        " Islamic seminaries": "List Of Islamic Seminaries"
    },
    {
        " Lutheran colleges and universities": "List Of Lutheran Colleges And Universities"
    },
    {
        " Muslim educational institutions": "List Of Muslim Educational Institutions"
    },
    {
        " Endowment": "Lists Of Institutions Of Higher Education By Endowment"
    },
    {
        " Largest universities by enrollment": "List Of Largest Universities By Enrollment"
    },
    {
        " Oldest madrasahs in continuous operation": "List Of Oldest Madrasahs In Continuous Operation"
    },
    {
        " Oldest universities in continuous operation": "List Of Oldest Universities In Continuous Operation"
    },
    {
        " Colleges and universities named after people": "List Of Colleges And Universities Named After People"
    },
    {
        " Medieval universities": "List Of Medieval Universities"
    },
    {
        " Ancient universities": "Ancient University"
    }
]