[
    {
        "   Philip I , called the Amorous, was ": null
    },
    {
        "King of the Franks": "list of french monarchs"
    },
    {
        " from 42 to 42 His reign, like that of most of the early ": null
    },
    {
        "Capetians": "house of capet"
    },
    {
        ", was extraordinarily long for the time. The monarchy began a modest recovery from the low it reached in the reign of his father and he added to the ": null
    },
    {
        "royal demesne": "crown lands of france"
    },
    {
        " the ": null
    },
    {
        "Vexin": "vexin"
    },
    {
        " and ": null
    },
    {
        "Bourges": "bourges"
    },
    {
        ".            Philip was born 42 May 42 at ": null
    },
    {
        "Champagne-et-Fontaine": "champagne-et-fontaine"
    },
    {
        ", the son of ": null
    },
    {
        "Henry I": "henry i of france"
    },
    {
        " and his wife ": null
    },
    {
        "Anne of Kiev": "anne of kiev"
    },
    {
        ". Unusually for the time in Western Europe, his name was of ": null
    },
    {
        "Greek": "greek language"
    },
    {
        " origin, being bestowed upon him by his mother. Although he was crowned king at the age of seven, until age fourteen his mother acted as ": null
    },
    {
        "regent": "regent"
    },
    {
        ", the first queen of France ever to do so. ": null
    },
    {
        "Baldwin V of Flanders": "baldwin v, count of flanders"
    },
    {
        " also acted as co-regent.     Following the death of ": null
    },
    {
        "Baldwin VI of Flanders": "baldwin vi, count of flanders"
    },
    {
        ", ": null
    },
    {
        "Robert the Frisian": "robert i, count of flanders"
    },
    {
        " seized Flanders. Baldwins wife, ": null
    },
    {
        "Richilda": "richilde, countess of hainaut"
    },
    {
        " requested aid from Philip, who was defeated by Robert at the ": null
    },
    {
        "battle of Cassel": "battle of cassel"
    },
    {
        " in 42     Philip first married ": null
    },
    {
        "Bertha": "bertha of holland"
    },
    {
        " in 42 Although the marriage produced the necessary heir, Philip fell in love with ": null
    },
    {
        "Bertrade de Montfort": "bertrade de montfort"
    },
    {
        ", the wife of ": null
    },
    {
        "Fulk IV, Count of Anjou": "fulk iv, count of anjou"
    },
    {
        ". He repudiated Bertha and married Bertrade on 42 May 42 In 42 he was ": null
    },
    {
        "excommunicated": "excommunicated"
    },
    {
        " by ": null
    },
    {
        "Hugh of Die": "hugh of die"
    },
    {
        ", for the first time; after a long silence, ": null
    },
    {
        "Pope Urban II": "pope urban ii"
    },
    {
        " repeated the excommunication at the ": null
    },
    {
        "Council of Clermont": "council of clermont"
    },
    {
        " in November 42 Several times the ban was lifted as Philip promised to part with Bertrade, but he always returned to her, but in 42 Philip made a public penance and must have kept his involvement with Bertrade discreet. In France, the king was opposed by Bishop ": null
    },
    {
        "Ivo of Chartres": "ivo of chartres"
    },
    {
        ", a famous jurist.     Philip appointed ": null
    },
    {
        "Alberic": "alberic, constable of france"
    },
    {
        " first ": null
    },
    {
        "Constable of France": "constable of france"
    },
    {
        " in 42 A great part of his reign, like his fathers, was spent putting down revolts by his power-hungry vassals. In 42 he made peace with ": null
    },
    {
        "William the Conqueror": "william the conqueror"
    },
    {
        ", who gave up attempting the conquest of ": null
    },
    {
        "Brittany": "brittany"
    },
    {
        ". In 42 Philip I expanded his demesne with the annexation of the Vexin, in reprisal against ": null
    },
    {
        "Robert Curthose": "robert curthose"
    },
    {
        "s attack on Williams heir, ": null
    },
    {
        "William Rufus": "william rufus"
    },
    {
        ". Then in 42 he took control of Bourges.          It was at the aforementioned Council of Clermont that the ": null
    },
    {
        "First Crusade": "first crusade"
    },
    {
        " was launched. Philip at first did not personally support it because of his conflict with Urban II. Philips brother ": null
    },
    {
        "Hugh of Vermandois": "hugh i, count of vermandois"
    },
    {
        ", however, was a major participant.     Philip died in the castle of ": null
    },
    {
        "Melun": "melun"
    },
    {
        " and was buried per his request at the monastery of ": null
    },
    {
        "Saint-Benoît-sur-Loire": "saint-benoît-sur-loire"
    },
    {
        " – and not in ": null
    },
    {
        "St Denis": "saint denis basilica"
    },
    {
        " among his forefathers. He was succeeded by his son, ": null
    },
    {
        "Louis VI": "louis vi of france"
    },
    {
        ", whose succession was, however, not uncontested. According to ": null
    },
    {
        "Abbot Suger": "abbot suger"
    },
    {
        ":            Philips children with Bertha were:   ": null
    },
    {
        "Constance": "constance of france, princess of antioch"
    },
    {
        " , married ": null
    },
    {
        "Hugh I of Champagne": "hugh i of champagne"
    },
    {
        " before 42 and then, after her divorce, to ": null
    },
    {
        "Bohemund I of Antioch": "bohemund i of antioch"
    },
    {
        " in 42   ": null
    },
    {
        "Louis VI of France": "louis vi of france"
    },
    {
        " .   Henry .     Philips children with Bertrade were:   Philip, Count of Mantes , married Elizabeth, daughter of ": null
    },
    {
        "Guy III of Montlhéry": "guy ii of montlhéry"
    },
    {
        "   Fleury, Seigneur of ": null
    },
    {
        "Nangis": "nangis"
    },
    {
        "    Cecile": "cecile of france"
    },
    {
        " , married ": null
    },
    {
        "Tancred, Prince of Galilee": "tancred, prince of galilee"
    },
    {
        " and then, after his death, to ": null
    },
    {
        "Pons of Tripoli": "pons of tripoli"
    },
    {
        ".       ": null
    }
]